buildout.cfg
setup.py
src/zc/__init__.py
src/zc.loggermonitor.egg-info/PKG-INFO
src/zc.loggermonitor.egg-info/SOURCES.txt
src/zc.loggermonitor.egg-info/dependency_links.txt
src/zc.loggermonitor.egg-info/entry_points.txt
src/zc.loggermonitor.egg-info/namespace_packages.txt
src/zc.loggermonitor.egg-info/not-zip-safe
src/zc.loggermonitor.egg-info/requires.txt
src/zc.loggermonitor.egg-info/top_level.txt
src/zc/loggermonitor/README.txt
src/zc/loggermonitor/__init__.py
src/zc/loggermonitor/configure.zcml
src/zc/loggermonitor/tests.py