Metadata-Version: 1.0
Name: zc.loggermonitor
Version: 0.1
Summary: UNKNOWN
Home-page: UNKNOWN
Author: Jim Fulton
Author-email: jim@zope.com
License: ZPL 2.1
Platform: UNKNOWN
